endecrypt.py
endecrypt-1.9.data/scripts/endecrypt.py
endecrypt-1.9.dist-info/METADATA
endecrypt-1.9.dist-info/WHEEL
endecrypt-1.9.dist-info/top_level.txt
endecrypt-1.9.dist-info/RECORD
