Metadata-Version: 2.1
Name: endecrypt
Version: 1.9
Summary: A simple python library for encryption and decryption . Library contain 10 (version 1.0) including ciphers and various other cryptography
Home-page: https://github.com/rajyavardhanb/endecrypt
Author: Rajyavardhan Bithale
Author-email: bithale03@protonmail.com
License: UNKNOWN
Platform: UNKNOWN
Classifier: Programming Language :: Python :: 3
Classifier: License :: OSI Approved :: MIT License
Classifier: Operating System :: OS Independent
Requires-Python: >=3.6
